deepresearch_mcp/__init__.py
deepresearch_mcp/__main__.py
deepresearch_mcp/server.py
deepresearch_mcp-0.2.0.dist-info/METADATA
deepresearch_mcp-0.2.0.dist-info/WHEEL
deepresearch_mcp-0.2.0.dist-info/entry_points.txt
deepresearch_mcp-0.2.0.dist-info/top_level.txt
deepresearch_mcp-0.2.0.dist-info/RECORD
