Metadata-Version: 2.4
Name: deepresearch-mcp
Version: 0.2.0
Summary: 实现类DeepResearch功能的MCP工具
Requires-Python: >=3.11
Requires-Dist: asyncio>=3.4.3
Requires-Dist: mcp>=1.9.1
Requires-Dist: openai>=1.82.0
Requires-Dist: openai-agents>=0.0.16
Requires-Dist: pydantic>=2.11.5
Requires-Dist: typing>=3.10.0.0
